welcome/__init__.py
welcome/mod_pack.py
welcome/first_pack/Minus.py
welcome/first_pack/Plus.py
welcome/first_pack/__init__.py
welcome/second_pack/Div.py
welcome/second_pack/__init__.py
welcome/second_pack/mul.py
PONDY-0.1.dist-info/LICENSE.txt
PONDY-0.1.dist-info/METADATA
PONDY-0.1.dist-info/WHEEL
PONDY-0.1.dist-info/top_level.txt
PONDY-0.1.dist-info/RECORD
